qwikstart/__init__.py
qwikstart/base_context.py
qwikstart/cli/__init__.py
qwikstart/cli/main.py
qwikstart/cli/resolver.py
qwikstart/cli/templates/operation_help.term
qwikstart/cli/utils.py
qwikstart/config.py
qwikstart/exceptions.py
qwikstart/operations/__init__.py
qwikstart/operations/add_file.py
qwikstart/operations/add_file_tree.py
qwikstart/operations/append_text.py
qwikstart/operations/base.py
qwikstart/operations/context_from_regex.py
qwikstart/operations/define_context.py
qwikstart/operations/echo.py
qwikstart/operations/edit_json.py
qwikstart/operations/edit_yaml.py
qwikstart/operations/find_files.py
qwikstart/operations/find_tag_and_insert_text.py
qwikstart/operations/find_tagged_line.py
qwikstart/operations/insert_text.py
qwikstart/operations/prompt.py
qwikstart/operations/search_and_replace.py
qwikstart/operations/shell.py
qwikstart/operations/subtask.py
qwikstart/operations/utils.py
qwikstart/parser.py
qwikstart/repository/__init__.py
qwikstart/repository/core.py
qwikstart/repository/git.py
qwikstart/repository/loaders.py
qwikstart/repository/yamllint.py
qwikstart/tasks.py
qwikstart/utils/__init__.py
qwikstart/utils/core.py
qwikstart/utils/dict_utils.py
qwikstart/utils/filesystem.py
qwikstart/utils/http.py
qwikstart/utils/input_types.py
qwikstart/utils/io.py
qwikstart/utils/logging.py
qwikstart/utils/prompt.py
qwikstart/utils/regex.py
qwikstart/utils/templates.py
qwikstart/utils/text_utils.py
qwikstart-0.8.0.dist-info/entry_points.txt
qwikstart-0.8.0.dist-info/LICENSE
qwikstart-0.8.0.dist-info/WHEEL
qwikstart-0.8.0.dist-info/METADATA
qwikstart-0.8.0.dist-info/RECORD
