Metadata-Version: 2.1
Name: qwikstart
Version: 0.8.0
Summary: Code generator for automating configuration, setup, and yak shaving.
Home-page: https://github.com/tonysyu/qwikstart
License: BSD-3-Clause
Keywords: console,terminal
Author: Tony S. Yu
Author-email: tsyu80@gmail.com
Requires-Python: >=3.7,<4.0
Classifier: Development Status :: 3 - Alpha
Classifier: Environment :: Console
Classifier: Intended Audience :: Developers
Classifier: License :: OSI Approved :: BSD License
Classifier: Programming Language :: Python :: 3
Classifier: Programming Language :: Python :: 3.10
Classifier: Programming Language :: Python :: 3.7
Classifier: Programming Language :: Python :: 3.8
Classifier: Programming Language :: Python :: 3.9
Classifier: Topic :: Software Development
Provides-Extra: docs
Requires-Dist: binaryornot (>=0.4.4,<0.5.0)
Requires-Dist: click (>=8.1.2,<9.0.0)
Requires-Dist: colorlog (>=6.6.0,<7.0.0)
Requires-Dist: dataclasses (>=0.7,<0.8); python_version >= "3.6" and python_version < "3.7"
Requires-Dist: gitpython (>=3.1.0,<4.0.0)
Requires-Dist: jinja2 (>=3.1.1,<4.0.0)
Requires-Dist: jinja2-time (>=0.2.0,<0.3.0)
Requires-Dist: prompt-toolkit (>=3.0.3,<4.0.0)
Requires-Dist: pygments (>=2.5.2,<3.0.0)
Requires-Dist: requests (>=2.23.0,<3.0.0)
Requires-Dist: rope (>=0.23.0,<0.24.0)
Requires-Dist: ruamel.yaml (>=0.17.21,<0.18.0)
Requires-Dist: sphinx (>=4.5.0,<5.0.0); extra == "docs"
Requires-Dist: sphinx-autobuild; extra == "docs"
Requires-Dist: sphinxcontrib-apidoc (>=0.3.0,<0.4.0); extra == "docs"
Requires-Dist: sphinxcontrib-napoleon; extra == "docs"
Requires-Dist: termcolor (>=1.1.0,<2.0.0)
Requires-Dist: typing-extensions (>=4.1.1,<5.0.0)
Requires-Dist: yamllint (>=1.23.0,<2.0.0)
Project-URL: Documentation, https://qwikstart.readthedocs.io/
Project-URL: Repository, https://github.com/tonysyu/qwikstart
